MANIFEST.in
setup.py
user_metrics/__init__.py
user_metrics/api/__init__.py
user_metrics/api/run.py
user_metrics/api/session.py
user_metrics/api/views.py
user_metrics/api/engine/__init__.py
user_metrics/api/engine/data.py
user_metrics/api/engine/request_manager.py
user_metrics/api/engine/request_meta.py
user_metrics/api/engine/response_handler.py
user_metrics/api/engine/response_meta.py
user_metrics/api/static/css/bootstrap.css
user_metrics/api/static/css/bootstrap.min.css
user_metrics/api/static/img/glyphicons-halflings-white.png
user_metrics/api/static/img/glyphicons-halflings.png
user_metrics/api/static/js/bootstrap.js
user_metrics/api/static/js/bootstrap.min.js
user_metrics/config/__init__.py
user_metrics/config/log.py
user_metrics/config/settings.py
user_metrics/etl/__init__.py
user_metrics/etl/aggregator.py
user_metrics/etl/data_loader.py
user_metrics/etl/log_parser.py
user_metrics/etl/table_loader.py
user_metrics/etl/time_series_process_methods.py
user_metrics/etl/wpapi.py
user_metrics/metrics/__init__.py
user_metrics/metrics/blocks.py
user_metrics/metrics/bytes_added.py
user_metrics/metrics/edit_count.py
user_metrics/metrics/edit_rate.py
user_metrics/metrics/live_account.py
user_metrics/metrics/namespace_of_edits.py
user_metrics/metrics/revert_rate.py
user_metrics/metrics/survival.py
user_metrics/metrics/threshold.py
user_metrics/metrics/time_to_threshold.py
user_metrics/metrics/user_metric.py
user_metrics/metrics/users.py
user_metrics/query/__init__.py
user_metrics/query/query_calls_noop.py
user_metrics/query/query_calls_sql.py
user_metrics/utils/__init__.py
user_metrics/utils/autovivification.py
user_metrics/utils/multiprocessing_wrapper.py
user_metrics/utils/record_type.py
wmf_user_metrics.egg-info/PKG-INFO
wmf_user_metrics.egg-info/SOURCES.txt
wmf_user_metrics.egg-info/dependency_links.txt
wmf_user_metrics.egg-info/requires.txt
wmf_user_metrics.egg-info/top_level.txt