Metadata-Version: 1.0
Name: wmf-user-metrics
Version: 0.1.4-dev
Summary: Data Analysis for Wikipedia User data.
Home-page: http://www.github.com/rfaulkner/E3_analysis
Author: Wikimedia Foundation
Author-email: e3-team@lists.wikimedia.org
License: UNKNOWN
Platform: UNKNOWN
Classifier: Development Status :: 1 - Planning
Classifier: Intended Audience :: Science/Research
Classifier: License :: OSI Approved :: GNU General Public License (GPL)
Classifier: Programming Language :: Python :: 2.6
Classifier: Programming Language :: Python :: 2.7
Classifier: Programming Language :: Python
Classifier: Topic :: Scientific/Engineering :: Information Analysis
Classifier: Topic :: Software Development :: Libraries :: Python Modules
